{
  "FormKey": "000820:HTG-System-Core.esp",
  "MajorRecordFlagsRaw": 9437696,
  "EditorID": "_ModInfo_HTG-System-Core",
  "StarfieldMajorRecordFlags": [
    "0x200",
    "0x100000",
    "0x800000"
  ],
  "VirtualMachineAdapter": {
    "Scripts": [
      {
        "Name": "HTG:SystemModuleInformation",
        "Properties": [
          {
            "MutagenObjectType": "ScriptStructProperty",
            "Name": "Version",
            "Members": [
              {
                "Name": "",
                "Properties": [
                  {
                    "MutagenObjectType": "ScriptIntProperty",
                    "Name": "Revision",
                    "Data": 6
                  }
                ]
              }
            ]
          },
          {
            "MutagenObjectType": "ScriptStringProperty",
            "Name": "Name",
            "Data": "HTG System Core"
          },
          {
            "MutagenObjectType": "ScriptObjectProperty",
            "Name": "SystemRegistry",
            "Object": "000837:HTG-System-Core.esp"
          },
          {
            "MutagenObjectType": "ScriptObjectProperty",
            "Name": "LocalSystemRegistry",
            "Object": "00081D:HTG-System-Core.esp"
          },
          {
            "MutagenObjectType": "ScriptStringProperty",
            "Name": "description",
            "Data": ""
          },
          {
            "MutagenObjectType": "ScriptObjectProperty",
            "Name": "ModuleRegistry",
            "Object": "000832:HTG-System-Core.esp"
          },
          {
            "MutagenObjectType": "ScriptObjectProperty",
            "Name": "CollectionRegistry",
            "Object": "000828:HTG-System-Core.esp"
          }
        ]
      }
    ]
  },
  "Name": {
    "TargetLanguage": "English",
    "Value": "Mod Information: HTG System Core"
  },
  "Model": {
    "LightLayer": 1
  },
  "Keywords": [
    "000839:HTG-System-Core.esp"
  ],
  "MarkerColor": "#00CC4C33",
  "Flags": [
    "IgnoredBySandbox"
  ],
  "ActivationAngle": 360,
  "MajorFlags": [
    "HiddenFromLocalMap",
    "IgnoreObjectInteraction",
    "IsMarker"
  ]
}